rlbandit/__init__.py
rlbandit/main.py
rlbandit-0.1.0.dist-info/METADATA
rlbandit-0.1.0.dist-info/WHEEL
rlbandit-0.1.0.dist-info/top_level.txt
rlbandit-0.1.0.dist-info/RECORD
