Metadata-Version: 2.1
Name: rlbandit
Version: 0.1.0
Summary: A simple epsilon-greedy multi-armed bandit RL example
Author: Your Name
License: MIT
Project-URL: Homepage, https://github.com/yourusername/rlbandit
Project-URL: Issues, https://github.com/yourusername/rlbandit/issues
Keywords: reinforcement-learning,epsilon-greedy,multi-armed-bandit
Classifier: Programming Language :: Python :: 3
Classifier: License :: OSI Approved :: MIT License
Requires-Python: >=3.8
